mint/__init__.py
mint/__main__.py
mint/_makeyaml.py
mint/_schema.py
mint/_utils.py
mint/downloader.py
mint/emulatorapi.py
mint/executor.py
mint/modelcatalogapi.py
mint/utils.py
mint_cli-2.1.0.dist-info/LICENSE
mint_cli-2.1.0.dist-info/METADATA
mint_cli-2.1.0.dist-info/WHEEL
mint_cli-2.1.0.dist-info/entry_points.txt
mint_cli-2.1.0.dist-info/top_level.txt
mint_cli-2.1.0.dist-info/RECORD
