Metadata-Version: 2.1
Name: mint-cli
Version: 2.1.0
Summary: A execution manager cli for execution
Home-page: https://github.com/mintproject/mint-execution-manager
Author: Maximiliano Osorio
Author-email: mosorio@isi.edu
License: Apache-2
Platform: UNKNOWN
Classifier: License :: OSI Approved :: Apache Software License
Classifier: Development Status :: 3 - Alpha
Classifier: Programming Language :: Python
Classifier: Programming Language :: Python :: 3
Classifier: Programming Language :: Python :: 3.5
Classifier: Programming Language :: Python :: 3.6
Classifier: Programming Language :: Python :: 3.7
Classifier: Intended Audience :: Science/Research
Classifier: Operating System :: Unix
Requires-Python: >=3.5.0
Requires-Dist: Click (>=7.0)
Requires-Dist: modelcatalog-api (>=1.7.0)
Requires-Dist: texttable (>=1.6.2)
Requires-Dist: validators (>=0.14.1)
Requires-Dist: ingestion-api (>=1.3.3)
Requires-Dist: PyYAML (>=5.1.2)
Requires-Dist: semver (>=2.8.1)
Requires-Dist: requests
Requires-Dist: jsonschema (>=3.0.0)
Requires-Dist: certifi (>=2019.11.28)
